picovoicedemo/LICENSE
picovoicedemo/picovoice_demo_file.py
picovoicedemo/picovoice_demo_mic.py
picovoicedemo-3.0.4.dist-info/METADATA
picovoicedemo-3.0.4.dist-info/WHEEL
picovoicedemo-3.0.4.dist-info/entry_points.txt
picovoicedemo-3.0.4.dist-info/top_level.txt
picovoicedemo-3.0.4.dist-info/RECORD
