Metadata-Version: 2.1
Name: picovoicedemo
Version: 3.0.4
Summary: ⚠️ DEPRECATED: This package has been deprecated and is no longer maintained.
Home-page: https://github.com/Picovoice/picovoice
Author: Picovoice Inc.
Author-email: hello@picovoice.ai
Keywords: wake word,voice control,speech recognition,voice recognition,natural language understanding
Classifier: Development Status :: 7 - Inactive
Requires-Python: >=3.8
Requires-Dist: picovoice (==3.0.3)
Requires-Dist: pvrecorder (==1.2.2)
